behavioural_d_ff/design.sv
module d_flip_flop (
  input d, clk,
  output reg q, qbar
);

  always @(posedge clk) begin
    q = d;
    qbar = ~q;
  end
  
endmodule

behavioral_d_ff/testbench.sv
`timescale 1ns/100ps

module d_flip_flop_tb();
  
  reg d_tb, clk_tb;
  wire q_tb, qbar_tb;
  
  d_flip_flop dff (d_tb, clk_tb, q_tb, qbar_tb);

  initial begin
  	clk_tb = 0;
  end
  
  always begin
    #10
    clk_tb = ~clk_tb;
  end
  
  initial begin
    $dumpfile("dump.vcd");
    $dumpvars;
 
    d_tb = 0;

    #100
    d_tb = 1;
    
    #100
    d_tb = 0;
    
    #100
    d_tb = 1;
    
    #100
    $finish;
  end
  
endmodule

behavioral_d_ff/dump.vcd
$date
	Tue Feb 15 22:36:14 2022
$end
$version
	Icarus Verilog
$end
$timescale
	100ps
$end
$scope module d_flip_flop_tb $end
$var wire 1 ! q_tb $end
$var wire 1 " qbar_tb $end
$var reg 1 # clk_tb $end
$var reg 1 $ d_tb $end
$scope module dff $end
$var wire 1 % clk $end
$var wire 1 & d $end
$var reg 1 ' q $end
$var reg 1 ( qbar $end
$upscope $end
$upscope $end
$enddefinitions $end
#0
$dumpvars
x(
x'
0&
0%
0$
0#
x"
x!
$end
#100
1(
1"
0'
0!
1#
1%
#200
0#
0%
#300
1#
1%
#400
0#
0%
#500
1#
1%
#600
0#
0%
#700
1#
1%
#800
0#
0%
#900
1#
1%
#1000
0#
0%
1$
1&
#1100
0(
0"
1'
1!
1#
1%
#1200
0#
0%
#1300
1#
1%
#1400
0#
0%
#1500
1#
1%
#1600
0#
0%
#1700
1#
1%
#1800
0#
0%
#1900
1#
1%
#2000
0#
0%
0$
0&
#2100
1(
1"
0'
0!
1#
1%
#2200
0#
0%
#2300
1#
1%
#2400
0#
0%
#2500
1#
1%
#2600
0#
0%
#2700
1#
1%
#2800
0#
0%
#2900
1#
1%
#3000
0#
0%
1$
1&
#3100
0(
0"
1'
1!
1#
1%
