otp_cypher/design.sv
/*
  @input clk (clock) -> LFSR just changes it state at positive edges of the clock
  @input clear -> when high, set all LFSR output to 1
  @input s0, s1 -> control if LFSR will load a new input or shift its output
  @input in (input) -> input to be loaded
  @output l_out (left out) -> returned value after shift left
  @output r_out (right out) -> returned value after shift right
  @output out -> full output
*/
module lfsr_8bit(
  clk,
  clear,
  s0,
  s1,
  in,
  l_out,
  r_out,
  out,
);
  localparam LFSR_SIZE = 8, MOST_SIGNIFICANT = 7, LEAST_SIGNIFICANT = 0, MAX = 8'b11111111;

  input clk, clear, s0, s1;
  input [LFSR_SIZE-1:0] in;
  output reg l_out, r_out;
  output reg [LFSR_SIZE-1:0] out;

  // l_in (left in) used when shifting right
  // r_in (right in) used when shifting left
  wire l_in, r_in;

  // assign new data while shifting
  assign l_in = (out[LEAST_SIGNIFICANT] ^ out[LEAST_SIGNIFICANT+1]);
  assign r_in = (out[MOST_SIGNIFICANT] ^ out[MOST_SIGNIFICANT-1]);

  // positive edge triggered
  always @(posedge clk) begin
    // set max value
    if (clear)
      out <= MAX;
    
    // load new input
    else if (s0 && s1) begin
      l_out <= in[MOST_SIGNIFICANT];
      r_out <= in[LEAST_SIGNIFICANT];
      out <= in;
    end
    
    // shift left
    else if (s0 && !s1) begin
      l_out <= out[MOST_SIGNIFICANT];
      out <= {out[MOST_SIGNIFICANT-1:LEAST_SIGNIFICANT], r_in};
    end
    
    // shift right
    else if (!s0 && s1) begin
      r_out <= out[LEAST_SIGNIFICANT];
      out <= {l_in, out[MOST_SIGNIFICANT:LEAST_SIGNIFICANT+1]};
    end
    
    // else keep as it is
  end

endmodule

otp_cypher/testbench.sv
`timescale 1ns/100ps

module otp_enc_dec_tb;

  localparam LFSR_SIZE = 8, MSG_SIZE = 104;
  
  // variables to control encoding/decoding
  reg [MSG_SIZE-1:0] enc_msg, dec_msg;
  integer i;
  
  // variables to instantiate LFSR
  reg clk, s0, s1;
  reg [LFSR_SIZE-1:0] key_seed;
  wire key_digit;

  // lfst module
  lfsr_8bit lfsr(.clk(clk), .s0(s0), .s1(s1), .in(key_seed), .r_out(key_digit));
  
  // pulse clock
  always begin
    #10
    clk = ~clk;
  end

  initial begin
    set_epwave;
    set_clock;

    // encode and decode "Hello, World!" using 11111111 as LFSR seed
    generate_key(8'b11111111);
    encode(104'b01001000011001010110110001101100011011110010110000100000010101110110111101110010011011000110010000100001);
    generate_key(8'b11111111);
    decode;
    show_result;
    
    // encode and decode "BH eh nóis!!" using 10101010 as LFSR seed
    generate_key(8'b10101010);
    encode(104'b01000010010010000010000001100101011010000010000001101110110000111011001101101001011100110010000100100001);
    generate_key(8'b10101010);
    decode;
    show_result;
    
    $finish;
  end

  // generate time diagram
  task set_epwave;
    begin
      $dumpfile("dump.vcd");
      $dumpvars;
    end
  endtask 

  // initial clock value
  task set_clock;
    begin
      clk = 1'b0;
    end
  endtask
  
  // key generate strategy
  task generate_key(input [LFSR_SIZE-1:0] seed);
    begin
      s0 = 1'b1;
      s1 = 1'b1;
      key_seed = seed;
      #20
      s0 = 1'b0;
    end
  endtask
  
  // encode given message
  task encode(input [MSG_SIZE-1:0] msg);
    begin
      for (i = MSG_SIZE - 1; i >= 0; i = i - 1) begin
        #20
        enc_msg[i] = msg[i] ^ key_digit;
      end
    end
  endtask
  
  // decode previous encoded message
  task decode;
    begin
      for (i = MSG_SIZE - 1; i >= 0; i = i - 1) begin
        #20
        dec_msg[i] = enc_msg[i] ^ key_digit;
      end
    end
  endtask
  
  // print encoded and decoded messages
  task show_result;
    begin
      $display("\nEncoded message:\t%s", enc_msg);
      $display("Decoded message:\t%s", dec_msg);
    end
  endtask
  
endmodule

otp_enc_dec/dump.vcd
$date
	Tue Feb 15 22:34:59 2022
$end
$version
	Icarus Verilog
$end
$timescale
	100ps
$end
$scope module otp_enc_dec_tb $end
$var wire 1 ! key_digit $end
$var reg 1 " clk $end
$var reg 104 # dec_msg [103:0] $end
$var reg 104 $ enc_msg [103:0] $end
$var integer 32 % i [31:0] $end
$var reg 8 & key_seed [7:0] $end
$var reg 1 ' s0 $end
$var reg 1 ( s1 $end
$scope module lfsr $end
$var wire 1 ) clear $end
$var wire 1 * clk $end
$var wire 8 + in [7:0] $end
$var wire 1 , l_in $end
$var wire 1 - r_in $end
$var wire 1 . s0 $end
$var wire 1 / s1 $end
$var reg 1 0 l_out $end
$var reg 8 1 out [7:0] $end
$var reg 1 2 r_out $end
$upscope $end
$scope task decode $end
$upscope $end
$scope task encode $end
$var reg 104 3 msg [103:0] $end
$upscope $end
$scope task generate_key $end
$var reg 8 4 seed [7:0] $end
$upscope $end
$scope task set_clock $end
$upscope $end
$scope task set_epwave $end
$upscope $end
$scope task show_result $end
$upscope $end
$upscope $end
$enddefinitions $end
#0
$dumpvars
b11111111 4
bx 3
x2
bx 1
x0
1/
1.
x-
x,
b11111111 +
0*
z)
1(
1'
b11111111 &
bx %
bx $
bx #
0"
x!
$end
#100
0,
0-
b11111111 1
12
1!
10
1"
1*
#200
0"
0*
b1100111 %
b1001000011001010110110001101100011011110010110000100000010101110110111101110010011011000110010000100001 3
0'
0.
#300
1-
b1111111 1
1"
1*
#400
0"
0*
b1100110 %
b1xxxxxxxxxxxxxxxxxxxxxxxxxxxxxxxxxxxxxxxxxxxxxxxxxxxxxxxxxxxxxxxxxxxxxxxxxxxxxxxxxxxxxxxxxxxxxxxxxxxxxxx $
#500
0-
b111111 1
1"
1*
#600
0"
0*
b1100101 %
b10xxxxxxxxxxxxxxxxxxxxxxxxxxxxxxxxxxxxxxxxxxxxxxxxxxxxxxxxxxxxxxxxxxxxxxxxxxxxxxxxxxxxxxxxxxxxxxxxxxxxxx $
#700
b11111 1
1"
1*
#800
0"
0*
b1100100 %
b101xxxxxxxxxxxxxxxxxxxxxxxxxxxxxxxxxxxxxxxxxxxxxxxxxxxxxxxxxxxxxxxxxxxxxxxxxxxxxxxxxxxxxxxxxxxxxxxxxxxxx $
#900
b1111 1
1"
1*
#1000
0"
0*
b1100011 %
b1011xxxxxxxxxxxxxxxxxxxxxxxxxxxxxxxxxxxxxxxxxxxxxxxxxxxxxxxxxxxxxxxxxxxxxxxxxxxxxxxxxxxxxxxxxxxxxxxxxxxx $
#1100
b111 1
1"
1*
#1200
0"
0*
b1100010 %
b10110xxxxxxxxxxxxxxxxxxxxxxxxxxxxxxxxxxxxxxxxxxxxxxxxxxxxxxxxxxxxxxxxxxxxxxxxxxxxxxxxxxxxxxxxxxxxxxxxxxx $
#1300
b11 1
1"
1*
#1400
0"
0*
b1100001 %
b101101xxxxxxxxxxxxxxxxxxxxxxxxxxxxxxxxxxxxxxxxxxxxxxxxxxxxxxxxxxxxxxxxxxxxxxxxxxxxxxxxxxxxxxxxxxxxxxxxxx $
#1500
1,
b1 1
1"
1*
#1600
0"
0*
b1100000 %
b1011011xxxxxxxxxxxxxxxxxxxxxxxxxxxxxxxxxxxxxxxxxxxxxxxxxxxxxxxxxxxxxxxxxxxxxxxxxxxxxxxxxxxxxxxxxxxxxxxxx $
#1700
0,
1-
b10000000 1
1"
1*
#1800
0"
0*
b1011111 %
b10110111xxxxxxxxxxxxxxxxxxxxxxxxxxxxxxxxxxxxxxxxxxxxxxxxxxxxxxxxxxxxxxxxxxxxxxxxxxxxxxxxxxxxxxxxxxxxxxxx $
#1900
b1000000 1
02
0!
1"
1*
#2000
0"
0*
b1011110 %
b101101110xxxxxxxxxxxxxxxxxxxxxxxxxxxxxxxxxxxxxxxxxxxxxxxxxxxxxxxxxxxxxxxxxxxxxxxxxxxxxxxxxxxxxxxxxxxxxxx $
#2100
0-
b100000 1
1"
1*
#2200
0"
0*
b1011101 %
b1011011101xxxxxxxxxxxxxxxxxxxxxxxxxxxxxxxxxxxxxxxxxxxxxxxxxxxxxxxxxxxxxxxxxxxxxxxxxxxxxxxxxxxxxxxxxxxxxx $
#2300
b10000 1
1"
1*
#2400
0"
0*
b1011100 %
b10110111011xxxxxxxxxxxxxxxxxxxxxxxxxxxxxxxxxxxxxxxxxxxxxxxxxxxxxxxxxxxxxxxxxxxxxxxxxxxxxxxxxxxxxxxxxxxxx $
#2500
b1000 1
1"
1*
#2600
0"
0*
b1011011 %
b101101110110xxxxxxxxxxxxxxxxxxxxxxxxxxxxxxxxxxxxxxxxxxxxxxxxxxxxxxxxxxxxxxxxxxxxxxxxxxxxxxxxxxxxxxxxxxxx $
#2700
b100 1
1"
1*
#2800
0"
0*
b1011010 %
b1011011101100xxxxxxxxxxxxxxxxxxxxxxxxxxxxxxxxxxxxxxxxxxxxxxxxxxxxxxxxxxxxxxxxxxxxxxxxxxxxxxxxxxxxxxxxxxx $
#2900
1,
b10 1
1"
1*
#3000
0"
0*
b1011001 %
b10110111011001xxxxxxxxxxxxxxxxxxxxxxxxxxxxxxxxxxxxxxxxxxxxxxxxxxxxxxxxxxxxxxxxxxxxxxxxxxxxxxxxxxxxxxxxxx $
#3100
1-
b10000001 1
1"
1*
#3200
0"
0*
b1011000 %
b101101110110010xxxxxxxxxxxxxxxxxxxxxxxxxxxxxxxxxxxxxxxxxxxxxxxxxxxxxxxxxxxxxxxxxxxxxxxxxxxxxxxxxxxxxxxxx $
#3300
0,
0-
b11000000 1
12
1!
1"
1*
#3400
0"
0*
b1010111 %
b1011011101100100xxxxxxxxxxxxxxxxxxxxxxxxxxxxxxxxxxxxxxxxxxxxxxxxxxxxxxxxxxxxxxxxxxxxxxxxxxxxxxxxxxxxxxxx $
#3500
1-
b1100000 1
02
0!
1"
1*
#3600
0"
0*
b1010110 %
b10110111011001000xxxxxxxxxxxxxxxxxxxxxxxxxxxxxxxxxxxxxxxxxxxxxxxxxxxxxxxxxxxxxxxxxxxxxxxxxxxxxxxxxxxxxxx $
#3700
0-
b110000 1
1"
1*
#3800
0"
0*
b1010101 %
b101101110110010001xxxxxxxxxxxxxxxxxxxxxxxxxxxxxxxxxxxxxxxxxxxxxxxxxxxxxxxxxxxxxxxxxxxxxxxxxxxxxxxxxxxxxx $
#3900
b11000 1
1"
1*
#4000
0"
0*
b1010100 %
b1011011101100100011xxxxxxxxxxxxxxxxxxxxxxxxxxxxxxxxxxxxxxxxxxxxxxxxxxxxxxxxxxxxxxxxxxxxxxxxxxxxxxxxxxxxx $
#4100
b1100 1
1"
1*
#4200
0"
0*
b1010011 %
b10110111011001000110xxxxxxxxxxxxxxxxxxxxxxxxxxxxxxxxxxxxxxxxxxxxxxxxxxxxxxxxxxxxxxxxxxxxxxxxxxxxxxxxxxxx $
#4300
1,
b110 1
1"
1*
#4400
0"
0*
b1010010 %
b101101110110010001101xxxxxxxxxxxxxxxxxxxxxxxxxxxxxxxxxxxxxxxxxxxxxxxxxxxxxxxxxxxxxxxxxxxxxxxxxxxxxxxxxxx $
#4500
0,
1-
b10000011 1
1"
1*
#4600
0"
0*
b1010001 %
b1011011101100100011011xxxxxxxxxxxxxxxxxxxxxxxxxxxxxxxxxxxxxxxxxxxxxxxxxxxxxxxxxxxxxxxxxxxxxxxxxxxxxxxxxx $
#4700
1,
b1000001 1
12
1!
1"
1*
#4800
0"
0*
b1010000 %
b10110111011001000110111xxxxxxxxxxxxxxxxxxxxxxxxxxxxxxxxxxxxxxxxxxxxxxxxxxxxxxxxxxxxxxxxxxxxxxxxxxxxxxxxx $
#4900
0,
b10100000 1
1"
1*
#5000
0"
0*
b1001111 %
b101101110110010001101111xxxxxxxxxxxxxxxxxxxxxxxxxxxxxxxxxxxxxxxxxxxxxxxxxxxxxxxxxxxxxxxxxxxxxxxxxxxxxxxx $
#5100
b1010000 1
02
0!
1"
1*
#5200
0"
0*
b1001110 %
b1011011101100100011011110xxxxxxxxxxxxxxxxxxxxxxxxxxxxxxxxxxxxxxxxxxxxxxxxxxxxxxxxxxxxxxxxxxxxxxxxxxxxxxx $
#5300
0-
b101000 1
1"
1*
#5400
0"
0*
b1001101 %
b10110111011001000110111101xxxxxxxxxxxxxxxxxxxxxxxxxxxxxxxxxxxxxxxxxxxxxxxxxxxxxxxxxxxxxxxxxxxxxxxxxxxxxx $
#5500
b10100 1
1"
1*
#5600
0"
0*
b1001100 %
b101101110110010001101111011xxxxxxxxxxxxxxxxxxxxxxxxxxxxxxxxxxxxxxxxxxxxxxxxxxxxxxxxxxxxxxxxxxxxxxxxxxxxx $
#5700
1,
b1010 1
1"
1*
#5800
0"
0*
b1001011 %
b1011011101100100011011110110xxxxxxxxxxxxxxxxxxxxxxxxxxxxxxxxxxxxxxxxxxxxxxxxxxxxxxxxxxxxxxxxxxxxxxxxxxxx $
#5900
1-
b10000101 1
1"
1*
#6000
0"
0*
b1001010 %
b10110111011001000110111101101xxxxxxxxxxxxxxxxxxxxxxxxxxxxxxxxxxxxxxxxxxxxxxxxxxxxxxxxxxxxxxxxxxxxxxxxxxx $
#6100
0-
b11000010 1
12
1!
1"
1*
#6200
0"
0*
b1001001 %
b101101110110010001101111011010xxxxxxxxxxxxxxxxxxxxxxxxxxxxxxxxxxxxxxxxxxxxxxxxxxxxxxxxxxxxxxxxxxxxxxxxxx $
#6300
b11100001 1
02
0!
1"
1*
#6400
0"
0*
b1001000 %
b1011011101100100011011110110100xxxxxxxxxxxxxxxxxxxxxxxxxxxxxxxxxxxxxxxxxxxxxxxxxxxxxxxxxxxxxxxxxxxxxxxxx $
#6500
0,
b11110000 1
12
1!
1"
1*
#6600
0"
0*
b1000111 %
b10110111011001000110111101101001xxxxxxxxxxxxxxxxxxxxxxxxxxxxxxxxxxxxxxxxxxxxxxxxxxxxxxxxxxxxxxxxxxxxxxxx $
#6700
1-
b1111000 1
02
0!
1"
1*
#6800
0"
0*
b1000110 %
b101101110110010001101111011010010xxxxxxxxxxxxxxxxxxxxxxxxxxxxxxxxxxxxxxxxxxxxxxxxxxxxxxxxxxxxxxxxxxxxxxx $
#6900
0-
b111100 1
1"
1*
#7000
0"
0*
b1000101 %
b1011011101100100011011110110100101xxxxxxxxxxxxxxxxxxxxxxxxxxxxxxxxxxxxxxxxxxxxxxxxxxxxxxxxxxxxxxxxxxxxxx $
#7100
1,
b11110 1
1"
1*
#7200
0"
0*
b1000100 %
b10110111011001000110111101101001011xxxxxxxxxxxxxxxxxxxxxxxxxxxxxxxxxxxxxxxxxxxxxxxxxxxxxxxxxxxxxxxxxxxxx $
#7300
0,
1-
b10001111 1
1"
1*
#7400
0"
0*
b1000011 %
b101101110110010001101111011010010110xxxxxxxxxxxxxxxxxxxxxxxxxxxxxxxxxxxxxxxxxxxxxxxxxxxxxxxxxxxxxxxxxxxx $
#7500
b1000111 1
12
1!
1"
1*
#7600
0"
0*
b1000010 %
b1011011101100100011011110110100101100xxxxxxxxxxxxxxxxxxxxxxxxxxxxxxxxxxxxxxxxxxxxxxxxxxxxxxxxxxxxxxxxxxx $
#7700
0-
b100011 1
1"
1*
#7800
0"
0*
b1000001 %
b10110111011001000110111101101001011000xxxxxxxxxxxxxxxxxxxxxxxxxxxxxxxxxxxxxxxxxxxxxxxxxxxxxxxxxxxxxxxxxx $
#7900
1,
b10001 1
1"
1*
#8000
0"
0*
b1000000 %
b101101110110010001101111011010010110000xxxxxxxxxxxxxxxxxxxxxxxxxxxxxxxxxxxxxxxxxxxxxxxxxxxxxxxxxxxxxxxxx $
#8100
0,
1-
b10001000 1
1"
1*
#8200
0"
0*
b111111 %
b1011011101100100011011110110100101100000xxxxxxxxxxxxxxxxxxxxxxxxxxxxxxxxxxxxxxxxxxxxxxxxxxxxxxxxxxxxxxxx $
#8300
b1000100 1
02
0!
1"
1*
#8400
0"
0*
b111110 %
b10110111011001000110111101101001011000000xxxxxxxxxxxxxxxxxxxxxxxxxxxxxxxxxxxxxxxxxxxxxxxxxxxxxxxxxxxxxxx $
#8500
1,
0-
b100010 1
1"
1*
#8600
0"
0*
b111101 %
b101101110110010001101111011010010110000000xxxxxxxxxxxxxxxxxxxxxxxxxxxxxxxxxxxxxxxxxxxxxxxxxxxxxxxxxxxxxx $
#8700
1-
b10010001 1
1"
1*
#8800
0"
0*
b111100 %
b1011011101100100011011110110100101100000001xxxxxxxxxxxxxxxxxxxxxxxxxxxxxxxxxxxxxxxxxxxxxxxxxxxxxxxxxxxxx $
#8900
0,
0-
b11001000 1
12
1!
1"
1*
#9000
0"
0*
b111011 %
b10110111011001000110111101101001011000000011xxxxxxxxxxxxxxxxxxxxxxxxxxxxxxxxxxxxxxxxxxxxxxxxxxxxxxxxxxxx $
#9100
1-
b1100100 1
02
0!
1"
1*
#9200
0"
0*
b111010 %
b101101110110010001101111011010010110000000111xxxxxxxxxxxxxxxxxxxxxxxxxxxxxxxxxxxxxxxxxxxxxxxxxxxxxxxxxxx $
#9300
1,
0-
b110010 1
1"
1*
#9400
0"
0*
b111001 %
b1011011101100100011011110110100101100000001111xxxxxxxxxxxxxxxxxxxxxxxxxxxxxxxxxxxxxxxxxxxxxxxxxxxxxxxxxx $
#9500
1-
b10011001 1
1"
1*
#9600
0"
0*
b111000 %
b10110111011001000110111101101001011000000011110xxxxxxxxxxxxxxxxxxxxxxxxxxxxxxxxxxxxxxxxxxxxxxxxxxxxxxxxx $
#9700
0,
0-
b11001100 1
12
1!
1"
1*
#9800
0"
0*
b110111 %
b101101110110010001101111011010010110000000111101xxxxxxxxxxxxxxxxxxxxxxxxxxxxxxxxxxxxxxxxxxxxxxxxxxxxxxxx $
#9900
1,
1-
b1100110 1
02
0!
1"
1*
#10000
0"
0*
b110110 %
b1011011101100100011011110110100101100000001111010xxxxxxxxxxxxxxxxxxxxxxxxxxxxxxxxxxxxxxxxxxxxxxxxxxxxxxx $
#10100
0,
b10110011 1
1"
1*
#10200
0"
0*
b110101 %
b10110111011001000110111101101001011000000011110100xxxxxxxxxxxxxxxxxxxxxxxxxxxxxxxxxxxxxxxxxxxxxxxxxxxxxx $
#10300
1,
b1011001 1
12
1!
1"
1*
#10400
0"
0*
b110100 %
b101101110110010001101111011010010110000000111101000xxxxxxxxxxxxxxxxxxxxxxxxxxxxxxxxxxxxxxxxxxxxxxxxxxxxx $
#10500
0,
b10101100 1
1"
1*
#10600
0"
0*
b110011 %
b1011011101100100011011110110100101100000001111010001xxxxxxxxxxxxxxxxxxxxxxxxxxxxxxxxxxxxxxxxxxxxxxxxxxxx $
#10700
1,
b1010110 1
02
0!
1"
1*
#10800
0"
0*
b110010 %
b10110111011001000110111101101001011000000011110100010xxxxxxxxxxxxxxxxxxxxxxxxxxxxxxxxxxxxxxxxxxxxxxxxxxx $
#10900
0,
b10101011 1
1"
1*
#11000
0"
0*
b110001 %
b101101110110010001101111011010010110000000111101000100xxxxxxxxxxxxxxxxxxxxxxxxxxxxxxxxxxxxxxxxxxxxxxxxxx $
#11100
1,
b1010101 1
12
1!
1"
1*
#11200
0"
0*
b110000 %
b1011011101100100011011110110100101100000001111010001001xxxxxxxxxxxxxxxxxxxxxxxxxxxxxxxxxxxxxxxxxxxxxxxxx $
#11300
b10101010 1
1"
1*
#11400
0"
0*
b101111 %
b10110111011001000110111101101001011000000011110100010011xxxxxxxxxxxxxxxxxxxxxxxxxxxxxxxxxxxxxxxxxxxxxxxx $
#11500
0-
b11010101 1
02
0!
1"
1*
#11600
0"
0*
b101110 %
b101101110110010001101111011010010110000000111101000100110xxxxxxxxxxxxxxxxxxxxxxxxxxxxxxxxxxxxxxxxxxxxxxx $
#11700
b11101010 1
12
1!
1"
1*
#11800
0"
0*
b101101 %
b1011011101100100011011110110100101100000001111010001001100xxxxxxxxxxxxxxxxxxxxxxxxxxxxxxxxxxxxxxxxxxxxxx $
#11900
b11110101 1
02
0!
1"
1*
#12000
0"
0*
b101100 %
b10110111011001000110111101101001011000000011110100010011000xxxxxxxxxxxxxxxxxxxxxxxxxxxxxxxxxxxxxxxxxxxxx $
#12100
b11111010 1
12
1!
1"
1*
#12200
0"
0*
b101011 %
b101101110110010001101111011010010110000000111101000100110000xxxxxxxxxxxxxxxxxxxxxxxxxxxxxxxxxxxxxxxxxxxx $
#12300
b11111101 1
02
0!
1"
1*
#12400
0"
0*
b101010 %
b1011011101100100011011110110100101100000001111010001001100000xxxxxxxxxxxxxxxxxxxxxxxxxxxxxxxxxxxxxxxxxxx $
#12500
b11111110 1
12
1!
1"
1*
#12600
0"
0*
b101001 %
b10110111011001000110111101101001011000000011110100010011000000xxxxxxxxxxxxxxxxxxxxxxxxxxxxxxxxxxxxxxxxxx $
#12700
0,
b11111111 1
02
0!
1"
1*
#12800
0"
0*
b101000 %
b101101110110010001101111011010010110000000111101000100110000001xxxxxxxxxxxxxxxxxxxxxxxxxxxxxxxxxxxxxxxxx $
#12900
1-
b1111111 1
12
1!
1"
1*
#13000
0"
0*
b100111 %
b1011011101100100011011110110100101100000001111010001001100000010xxxxxxxxxxxxxxxxxxxxxxxxxxxxxxxxxxxxxxxx $
#13100
0-
b111111 1
1"
1*
#13200
0"
0*
b100110 %
b10110111011001000110111101101001011000000011110100010011000000101xxxxxxxxxxxxxxxxxxxxxxxxxxxxxxxxxxxxxxx $
#13300
b11111 1
1"
1*
#13400
0"
0*
b100101 %
b101101110110010001101111011010010110000000111101000100110000001010xxxxxxxxxxxxxxxxxxxxxxxxxxxxxxxxxxxxxx $
#13500
b1111 1
1"
1*
#13600
0"
0*
b100100 %
b1011011101100100011011110110100101100000001111010001001100000010100xxxxxxxxxxxxxxxxxxxxxxxxxxxxxxxxxxxxx $
#13700
b111 1
1"
1*
#13800
0"
0*
b100011 %
b10110111011001000110111101101001011000000011110100010011000000101001xxxxxxxxxxxxxxxxxxxxxxxxxxxxxxxxxxxx $
#13900
b11 1
1"
1*
#14000
0"
0*
b100010 %
b101101110110010001101111011010010110000000111101000100110000001010010xxxxxxxxxxxxxxxxxxxxxxxxxxxxxxxxxxx $
#14100
1,
b1 1
1"
1*
#14200
0"
0*
b100001 %
b1011011101100100011011110110100101100000001111010001001100000010100100xxxxxxxxxxxxxxxxxxxxxxxxxxxxxxxxxx $
#14300
0,
1-
b10000000 1
1"
1*
#14400
0"
0*
b100000 %
b10110111011001000110111101101001011000000011110100010011000000101001000xxxxxxxxxxxxxxxxxxxxxxxxxxxxxxxxx $
#14500
b1000000 1
02
0!
1"
1*
#14600
0"
0*
b11111 %
b101101110110010001101111011010010110000000111101000100110000001010010001xxxxxxxxxxxxxxxxxxxxxxxxxxxxxxxx $
#14700
0-
b100000 1
1"
1*
#14800
0"
0*
b11110 %
b1011011101100100011011110110100101100000001111010001001100000010100100010xxxxxxxxxxxxxxxxxxxxxxxxxxxxxxx $
#14900
b10000 1
1"
1*
#15000
0"
0*
b11101 %
b10110111011001000110111101101001011000000011110100010011000000101001000101xxxxxxxxxxxxxxxxxxxxxxxxxxxxxx $
#15100
b1000 1
1"
1*
#15200
0"
0*
b11100 %
b101101110110010001101111011010010110000000111101000100110000001010010001011xxxxxxxxxxxxxxxxxxxxxxxxxxxxx $
#15300
b100 1
1"
1*
#15400
0"
0*
b11011 %
b1011011101100100011011110110100101100000001111010001001100000010100100010111xxxxxxxxxxxxxxxxxxxxxxxxxxxx $
#15500
1,
b10 1
1"
1*
#15600
0"
0*
b11010 %
b10110111011001000110111101101001011000000011110100010011000000101001000101110xxxxxxxxxxxxxxxxxxxxxxxxxxx $
#15700
1-
b10000001 1
1"
1*
#15800
0"
0*
b11001 %
b101101110110010001101111011010010110000000111101000100110000001010010001011100xxxxxxxxxxxxxxxxxxxxxxxxxx $
#15900
0,
0-
b11000000 1
12
1!
1"
1*
#16000
0"
0*
b11000 %
b1011011101100100011011110110100101100000001111010001001100000010100100010111000xxxxxxxxxxxxxxxxxxxxxxxxx $
#16100
1-
b1100000 1
02
0!
1"
1*
#16200
0"
0*
b10111 %
b10110111011001000110111101101001011000000011110100010011000000101001000101110000xxxxxxxxxxxxxxxxxxxxxxxx $
#16300
0-
b110000 1
1"
1*
#16400
0"
0*
b10110 %
b101101110110010001101111011010010110000000111101000100110000001010010001011100000xxxxxxxxxxxxxxxxxxxxxxx $
#16500
b11000 1
1"
1*
#16600
0"
0*
b10101 %
b1011011101100100011011110110100101100000001111010001001100000010100100010111000001xxxxxxxxxxxxxxxxxxxxxx $
#16700
b1100 1
1"
1*
#16800
0"
0*
b10100 %
b10110111011001000110111101101001011000000011110100010011000000101001000101110000011xxxxxxxxxxxxxxxxxxxxx $
#16900
1,
b110 1
1"
1*
#17000
0"
0*
b10011 %
b101101110110010001101111011010010110000000111101000100110000001010010001011100000110xxxxxxxxxxxxxxxxxxxx $
#17100
0,
1-
b10000011 1
1"
1*
#17200
0"
0*
b10010 %
b1011011101100100011011110110100101100000001111010001001100000010100100010111000001101xxxxxxxxxxxxxxxxxxx $
#17300
1,
b1000001 1
12
1!
1"
1*
#17400
0"
0*
b10001 %
b10110111011001000110111101101001011000000011110100010011000000101001000101110000011010xxxxxxxxxxxxxxxxxx $
#17500
0,
b10100000 1
1"
1*
#17600
0"
0*
b10000 %
b101101110110010001101111011010010110000000111101000100110000001010010001011100000110101xxxxxxxxxxxxxxxxx $
#17700
b1010000 1
02
0!
1"
1*
#17800
0"
0*
b1111 %
b1011011101100100011011110110100101100000001111010001001100000010100100010111000001101010xxxxxxxxxxxxxxxx $
#17900
0-
b101000 1
1"
1*
#18000
0"
0*
b1110 %
b10110111011001000110111101101001011000000011110100010011000000101001000101110000011010100xxxxxxxxxxxxxxx $
#18100
b10100 1
1"
1*
#18200
0"
0*
b1101 %
b101101110110010001101111011010010110000000111101000100110000001010010001011100000110101001xxxxxxxxxxxxxx $
#18300
1,
b1010 1
1"
1*
#18400
0"
0*
b1100 %
b1011011101100100011011110110100101100000001111010001001100000010100100010111000001101010011xxxxxxxxxxxxx $
#18500
1-
b10000101 1
1"
1*
#18600
0"
0*
b1011 %
b10110111011001000110111101101001011000000011110100010011000000101001000101110000011010100110xxxxxxxxxxxx $
#18700
0-
b11000010 1
12
1!
1"
1*
#18800
0"
0*
b1010 %
b101101110110010001101111011010010110000000111101000100110000001010010001011100000110101001101xxxxxxxxxxx $
#18900
b11100001 1
02
0!
1"
1*
#19000
0"
0*
b1001 %
b1011011101100100011011110110100101100000001111010001001100000010100100010111000001101010011011xxxxxxxxxx $
#19100
0,
b11110000 1
12
1!
1"
1*
#19200
0"
0*
b1000 %
b10110111011001000110111101101001011000000011110100010011000000101001000101110000011010100110111xxxxxxxxx $
#19300
1-
b1111000 1
02
0!
1"
1*
#19400
0"
0*
b111 %
b101101110110010001101111011010010110000000111101000100110000001010010001011100000110101001101110xxxxxxxx $
#19500
0-
b111100 1
1"
1*
#19600
0"
0*
b110 %
b1011011101100100011011110110100101100000001111010001001100000010100100010111000001101010011011100xxxxxxx $
#19700
1,
b11110 1
1"
1*
#19800
0"
0*
b101 %
b10110111011001000110111101101001011000000011110100010011000000101001000101110000011010100110111000xxxxxx $
#19900
0,
1-
b10001111 1
1"
1*
#20000
0"
0*
b100 %
b101101110110010001101111011010010110000000111101000100110000001010010001011100000110101001101110001xxxxx $
#20100
b1000111 1
12
1!
1"
1*
#20200
0"
0*
b11 %
b1011011101100100011011110110100101100000001111010001001100000010100100010111000001101010011011100011xxxx $
#20300
0-
b100011 1
1"
1*
#20400
0"
0*
b10 %
b10110111011001000110111101101001011000000011110100010011000000101001000101110000011010100110111000111xxx $
#20500
1,
b10001 1
1"
1*
#20600
0"
0*
b1 %
b101101110110010001101111011010010110000000111101000100110000001010010001011100000110101001101110001111xx $
#20700
0,
1-
b10001000 1
1"
1*
#20800
0"
0*
b0 %
b1011011101100100011011110110100101100000001111010001001100000010100100010111000001101010011011100011111x $
#20900
b1000100 1
02
0!
1"
1*
#21000
0"
0*
1'
1.
b11111111111111111111111111111111 %
b10110111011001000110111101101001011000000011110100010011000000101001000101110000011010100110111000111111 $
#21100
0-
b11111111 1
12
1!
1"
1*
#21200
0"
0*
b1100111 %
0'
0.
#21300
1-
b1111111 1
1"
1*
#21400
0"
0*
b1100110 %
b0xxxxxxxxxxxxxxxxxxxxxxxxxxxxxxxxxxxxxxxxxxxxxxxxxxxxxxxxxxxxxxxxxxxxxxxxxxxxxxxxxxxxxxxxxxxxxxxxxxxxxxx #
#21500
0-
b111111 1
1"
1*
#21600
0"
0*
b1100101 %
b1xxxxxxxxxxxxxxxxxxxxxxxxxxxxxxxxxxxxxxxxxxxxxxxxxxxxxxxxxxxxxxxxxxxxxxxxxxxxxxxxxxxxxxxxxxxxxxxxxxxxxx #
#21700
b11111 1
1"
1*
#21800
0"
0*
b1100100 %
b10xxxxxxxxxxxxxxxxxxxxxxxxxxxxxxxxxxxxxxxxxxxxxxxxxxxxxxxxxxxxxxxxxxxxxxxxxxxxxxxxxxxxxxxxxxxxxxxxxxxxx #
#21900
b1111 1
1"
1*
#22000
0"
0*
b1100011 %
b100xxxxxxxxxxxxxxxxxxxxxxxxxxxxxxxxxxxxxxxxxxxxxxxxxxxxxxxxxxxxxxxxxxxxxxxxxxxxxxxxxxxxxxxxxxxxxxxxxxxx #
#22100
b111 1
1"
1*
#22200
0"
0*
b1100010 %
b1001xxxxxxxxxxxxxxxxxxxxxxxxxxxxxxxxxxxxxxxxxxxxxxxxxxxxxxxxxxxxxxxxxxxxxxxxxxxxxxxxxxxxxxxxxxxxxxxxxxx #
#22300
b11 1
1"
1*
#22400
0"
0*
b1100001 %
b10010xxxxxxxxxxxxxxxxxxxxxxxxxxxxxxxxxxxxxxxxxxxxxxxxxxxxxxxxxxxxxxxxxxxxxxxxxxxxxxxxxxxxxxxxxxxxxxxxxx #
#22500
1,
b1 1
1"
1*
#22600
0"
0*
b1100000 %
b100100xxxxxxxxxxxxxxxxxxxxxxxxxxxxxxxxxxxxxxxxxxxxxxxxxxxxxxxxxxxxxxxxxxxxxxxxxxxxxxxxxxxxxxxxxxxxxxxxx #
